fast_bi_replication_control/__init__.py
fast_bi_replication_control/airbyte/__init__.py
fast_bi_replication_control/airbyte/hook.py
fast_bi_replication_control/airbyte/job_tracker.py
fast_bi_replication_control/airbyte/operator.py
fast_bi_replication_control/airbyte/sensor.py
fast_bi_replication_control-0.1.0.dist-info/METADATA
fast_bi_replication_control-0.1.0.dist-info/WHEEL
fast_bi_replication_control-0.1.0.dist-info/top_level.txt
fast_bi_replication_control-0.1.0.dist-info/RECORD
