Metadata-Version: 2.4
Name: fast-bi-replication-control
Version: 0.1.0
Summary: Airflow utilities to monitor and cancel long-running Airbyte jobs with advanced job tracking
Author-email: "Fast.BI" <support@fast.bi>
Maintainer-email: "Fast.BI" <administrator@fast.bi>
License: MIT
Project-URL: Homepage, https://github.com/fast-bi/data-replication-control
Project-URL: Documentation, https://wiki.fast.bi/en/User-Guide/Data-Orchestration/Data-Replication-Control
Project-URL: Repository, https://github.com/fast-bi/data-replication-control
Project-URL: Bug Tracker, https://github.com/fast-bi/data-replication-control/issues
Project-URL: Changelog, https://github.com/fast-bi/data-replication-control/blob/master/CHANGELOG.md
Keywords: airflow,airbyte,data-replication,job-monitoring,job-tracking,etl,data-pipeline,fast-bi,data-orchestration,workflow,data-workflow
Classifier: Development Status :: 4 - Beta
Classifier: Intended Audience :: Developers
Classifier: Intended Audience :: Information Technology
Classifier: License :: OSI Approved :: MIT License
Classifier: Operating System :: OS Independent
Classifier: Programming Language :: Python :: 3
Classifier: Programming Language :: Python :: 3.8
Classifier: Programming Language :: Python :: 3.9
Classifier: Programming Language :: Python :: 3.10
Classifier: Programming Language :: Python :: 3.11
Classifier: Programming Language :: Python :: 3.12
Classifier: Topic :: Database
Classifier: Topic :: Scientific/Engineering :: Information Analysis
Classifier: Topic :: Software Development :: Libraries :: Python Modules
Classifier: Topic :: System :: Distributed Computing
Classifier: Framework :: Apache Airflow
Classifier: Topic :: Software Development :: Testing
Classifier: Topic :: Software Development :: Quality Assurance
Requires-Python: <3.13,>=3.9
Requires-Dist: apache-airflow>=2.6.0
Requires-Dist: requests>=2.31.0
Provides-Extra: dev
Requires-Dist: black>=21.0.0; extra == "dev"
Requires-Dist: flake8>=3.8.0; extra == "dev"
Requires-Dist: mypy>=0.800; extra == "dev"
Requires-Dist: pre-commit>=2.15.0; extra == "dev"
Requires-Dist: twine>=3.0.0; extra == "dev"
Requires-Dist: wheel>=0.37.0; extra == "dev"
Provides-Extra: docs
Requires-Dist: sphinx>=4.0.0; extra == "docs"
Requires-Dist: sphinx-rtd-theme>=1.0.0; extra == "docs"
Requires-Dist: myst-parser>=0.15.0; extra == "docs"
